rundeck/__init__.py
rundeck/base.py
rundeck/client.py
rundeck/config.py
rundeck/const.py
rundeck/exceptions.py
rundeck/py.typed
rundeck/v1/__init__.py
rundeck/v1/objects/__init__.py
rundeck/v1/objects/adhoc.py
rundeck/v1/objects/config_management.py
rundeck/v1/objects/executions.py
rundeck/v1/objects/features.py
rundeck/v1/objects/jobs.py
rundeck/v1/objects/key_storage.py
rundeck/v1/objects/metrics.py
rundeck/v1/objects/plugins.py
rundeck/v1/objects/projects.py
rundeck/v1/objects/scheduler.py
rundeck/v1/objects/scm.py
rundeck/v1/objects/system.py
rundeck/v1/objects/tokens.py
rundeck/v1/objects/users.py
rundeck/v1/objects/webhooks.py
python_rundeck-1.0.1.dist-info/METADATA
python_rundeck-1.0.1.dist-info/WHEEL
python_rundeck-1.0.1.dist-info/licenses/LICENSE
python_rundeck-1.0.1.dist-info/RECORD
