Metadata-Version: 2.4
Name: python-rundeck
Version: 1.0.1
Summary: Python client for the Rundeck API (v14-v56).
License-Expression: MIT
License-File: LICENSE
Keywords: rundeck,api,client
Author: Pascal Seckinger
Author-email: pascal.seckinger@protonmail.com
Requires-Python: >=3.11
Classifier: Development Status :: 5 - Production/Stable
Classifier: Intended Audience :: Developers
Classifier: License :: OSI Approved :: MIT License
Classifier: Operating System :: OS Independent
Classifier: Programming Language :: Python :: 3
Classifier: Programming Language :: Python :: 3.11
Classifier: Programming Language :: Python :: 3.12
Classifier: Programming Language :: Python :: 3.13
Classifier: Topic :: Software Development :: Libraries
Classifier: Topic :: System :: Systems Administration
Classifier: Typing :: Typed
Provides-Extra: dev
Requires-Dist: bandit (>=1.7.9,<2.0.0) ; extra == "dev"
Requires-Dist: black (>=25.11.0,<26.0.0) ; extra == "dev"
Requires-Dist: flake8 (>=7.0.0,<8.0.0) ; extra == "dev"
Requires-Dist: isort (>=7.0.0,<8.0.0) ; extra == "dev"
Requires-Dist: pytest (>=9.0.2,<10.0.0) ; extra == "dev"
Requires-Dist: pytest-cov (>=5.0.0,<6.0.0) ; extra == "dev"
Requires-Dist: requests (>=2.32.5,<3.0.0)
Requires-Dist: ruff (>=0.7.0,<1.0.0) ; extra == "dev"
Requires-Dist: safety (>=3.2.0,<4.0.0) ; extra == "dev"
Project-URL: Changelog, https://gitlab.com/pascal.seckinger/python-rundeck/-/blob/main/CHANGELOG.md
Project-URL: Documentation, https://gitlab.com/pascal.seckinger/python-rundeck/-/blob/main/README.md
Project-URL: Homepage, https://gitlab.com/pascal.seckinger/python-rundeck
Project-URL: Issues, https://gitlab.com/pascal.seckinger/python-rundeck/-/issues
Project-URL: Repository, https://gitlab.com/pascal.seckinger/python-rundeck
